adcm_client/__init__.py
adcm_client/audit.py
adcm_client/base.py
adcm_client/mapper.py
adcm_client/objects.py
adcm_client/packer/__init__.py
adcm_client/packer/add_to_tar.py
adcm_client/packer/bundle_build.py
adcm_client/packer/naming_rules.py
adcm_client/packer/spec.py
adcm_client/packer/types.py
adcm_client/packer/data/__init__.py
adcm_client/packer/data/config_data.py
adcm_client/util/__init__.py
adcm_client/util/config.py
adcm_client/util/conftest.py
adcm_client/util/search.py
adcm_client/util/stream.py
adcm_client/util/test_search.py
adcm_client/util/wait.py
adcm_client/wrappers/__init__.py
adcm_client/wrappers/api.py
adcm_client/wrappers/docker.py
adcm_client-2023.12.28.15.data/scripts/adcm_sdk_pack
adcm_client-2023.12.28.15.data/scripts/adcm_sdk_shell
adcm_client-2023.12.28.15.dist-info/LICENSE
adcm_client-2023.12.28.15.dist-info/METADATA
adcm_client-2023.12.28.15.dist-info/WHEEL
adcm_client-2023.12.28.15.dist-info/top_level.txt
adcm_client-2023.12.28.15.dist-info/RECORD
