Metadata-Version: 2.1
Name: adcm-client
Version: 2023.12.28.15
Summary: ArenaData Cluster Manager Client
Home-page: https://github.com/arenadata/adcm
Author: Anton Chevychalov
Author-email: cab@arenadata.io
Classifier: Programming Language :: Python :: 3
Classifier: License :: OSI Approved :: Apache Software License
Classifier: Operating System :: OS Independent
Requires-Python: >=3.8
License-File: LICENSE
Requires-Dist: pyyaml
Requires-Dist: coreapi
Requires-Dist: ipython
Requires-Dist: ad-ci-tools ==0.1.9
Requires-Dist: docker
Requires-Dist: jinja2
Requires-Dist: adcm-version <2.0
Provides-Extra: setup
Requires-Dist: ad-ci-tools ==0.1.9 ; extra == 'setup'
Requires-Dist: pytz ; extra == 'setup'
Requires-Dist: setuptools ; extra == 'setup'
Requires-Dist: wheel ; extra == 'setup'
Provides-Extra: test
Requires-Dist: pytest ; extra == 'test'
